LICENSE.txt
MANIFEST.in
README.md
README.rst
blog-post.md
blog-post.rst
setup.py
markdust/__init__.py
markdust/__version__.py
markdust/cl_utils.py
markdust/default_settings.yaml
markdust/utKit.py
markdust.egg-info/PKG-INFO
markdust.egg-info/SOURCES.txt
markdust.egg-info/dependency_links.txt
markdust.egg-info/entry_points.txt
markdust.egg-info/not-zip-safe
markdust.egg-info/requires.txt
markdust.egg-info/top_level.txt
markdust/bible/__init__.py
markdust/bible/esv.py
markdust/bible/tests/__init__.py
markdust/bible/tests/test_esv.py
markdust/bible/tests/input/example_settings.yaml
markdust/bible/tests/output/example_settings.yaml
markdust/commonutils/__init__.py
markdust/commonutils/getpackagepath.py
markdust/tests/__init__.py