Metadata-Version: 1.1
Name: markdust
Version: 0.2.0
Summary: A python package and command-line tools to A bunch of scripts and command-line tools to help with writting notes, blog-posts and slides
Home-page: https://github.com/thespacedoctor/markdust
Author: David Young
Author-email: davidrobertyoung@gmail.com
License: MIT
Download-URL: https://github.com/thespacedoctor/markdust/archive/v0.2.0.zip
Keywords: markdown
Platform: UNKNOWN
Classifier: Development Status :: 4 - Beta
Classifier: License :: OSI Approved :: MIT License
Classifier: Programming Language :: Python :: 2.7
Classifier: Topic :: Utilities
